LICENSE
begin/__init__.py
begin/cli/__init__.py
begin/cli/cli.py
begin/cli/parser.py
begin/constants.py
begin/exceptions.py
begin/recipes.py
begin/registry.py
begin_cli-0.4.0.dist-info/entry_points.txt
begin_cli-0.4.0.dist-info/LICENSE
begin_cli-0.4.0.dist-info/WHEEL
begin_cli-0.4.0.dist-info/METADATA
begin_cli-0.4.0.dist-info/RECORD
