Metadata-Version: 2.1
Name: begin-cli
Version: 0.4.0
Summary: A utility for running targets in a targets.py file
Home-page: https://github.com/LachlanMarnham/begin
License: MIT
Author: Lachlan Marnham
Maintainer: Lachlan Marnham
Requires-Python: >=3.7,<4.0
Classifier: License :: OSI Approved :: MIT License
Classifier: Programming Language :: Python :: 3
Classifier: Programming Language :: Python :: 3.10
Classifier: Programming Language :: Python :: 3.7
Classifier: Programming Language :: Python :: 3.8
Classifier: Programming Language :: Python :: 3.9
Project-URL: Repository, https://github.com/LachlanMarnham/begin
